{
    "url": "https://forms.gle/qFkBDjWP1HCVDM2V8",
    "lists": [
        {
            "xpath": "//div[@role='list']",
            "questions": [
                {
                    "xpath": "./div[@role='listitem']",
                    "type": "",
                    "heading": "",
                    "options": [],
                    "scale": [],
                    "rows": [],
                    "columns": []
                },
                {
                    "xpath": "./div[@role='listitem']",
                    "type": "",
                    "heading": "",
                    "options": [],
                    "scale": [],
                    "rows": [],
                    "columns": []
                },
                {
                    "xpath": "./div[@role='listitem']",
                    "type": "",
                    "heading": "",
                    "options": [],
                    "scale": [],
                    "rows": [],
                    "columns": []
                },
                {
                    "xpath": "./div[@role='listitem']",
                    "type": "",
                    "heading": "",
                    "options": [],
                    "scale": [],
                    "rows": [],
                    "columns": []
                },
                {
                    "xpath": "./div[@role='listitem']",
                    "type": "",
                    "heading": "",
                    "options": [],
                    "scale": [],
                    "rows": [],
                    "columns": []
                },
                {
                    "xpath": "./div[@role='listitem']",
                    "type": "",
                    "heading": "",
                    "options": [],
                    "scale": [],
                    "rows": [],
                    "columns": []
                },
                {
                    "xpath": "./div[@role='listitem']",
                    "type": "",
                    "heading": "",
                    "options": [],
                    "scale": [],
                    "rows": [],
                    "columns": []
                },
                {
                    "xpath": "./div[@role='listitem']",
                    "type": "",
                    "heading": "",
                    "options": [],
                    "scale": [],
                    "rows": [],
                    "columns": []
                },
                {
                    "xpath": "./div[@role='listitem']",
                    "type": "",
                    "heading": "",
                    "options": [],
                    "scale": [],
                    "rows": [],
                    "columns": []
                },
                {
                    "xpath": "./div[@role='listitem']",
                    "type": "",
                    "heading": "",
                    "options": [],
                    "scale": [],
                    "rows": [],
                    "columns": []
                },
                {
                    "xpath": "./div[@role='listitem']",
                    "type": "",
                    "heading": "",
                    "options": [],
                    "scale": [],
                    "rows": [],
                    "columns": []
                },
                {
                    "xpath": "./div[@role='listitem']",
                    "type": "",
                    "heading": "",
                    "options": [],
                    "scale": [],
                    "rows": [],
                    "columns": []
                }
            ],
            "button": {
                "value": "Submit",
                "xpath": "//div[@role='button' and contains(@aria-label, 'Submit')]"
            }
        }
    ]
}